bpdfr_discovery/__init__.py
bpdfr_discovery/emd_metric.py
bpdfr_discovery/exceptions.py
bpdfr_discovery/inter_arrival_cases_discovery.py
bpdfr_discovery/log_comparison_metrics.py
bpdfr_discovery/log_parser.py
cli/__init__.py
cli/diff_res_bpsim.py
prosimos/__init__.py
prosimos/all_attributes.py
prosimos/batch_processing.py
prosimos/batch_processing_parser.py
prosimos/branch_condition_parser.py
prosimos/branch_condition_rules.py
prosimos/case_attributes.py
prosimos/control_flow_manager.py
prosimos/event_attributes.py
prosimos/event_attributes_parser.py
prosimos/exceptions.py
prosimos/execution_info.py
prosimos/file_manager.py
prosimos/fuzzy_engine/event_log_analyser.py
prosimos/fuzzy_engine/fuzzy_calendar.py
prosimos/gateway_condition_choice.py
prosimos/global_attributes.py
prosimos/global_attributes_parser.py
prosimos/histogram_distribution.py
prosimos/outgoing_flow_selector.py
prosimos/prioritisation.py
prosimos/prioritisation_parser.py
prosimos/prioritisation_rules.py
prosimos/probability_distributions.py
prosimos/resource_profile.py
prosimos/simulation_engine.py
prosimos/simulation_execution_stats.py
prosimos/simulation_properties_parser.py
prosimos/simulation_queues_ds.py
prosimos/simulation_setup.py
prosimos/simulation_stats.py
prosimos/simulation_stats_calculator.py
prosimos/warning_logger.py
prosimos/weekday_helper.py
prosimos-2.0.6.dist-info/METADATA
prosimos-2.0.6.dist-info/WHEEL
prosimos-2.0.6.dist-info/entry_points.txt
prosimos-2.0.6.dist-info/RECORD
