Metadata-Version: 2.1
Name: prosimos
Version: 2.0.6
Summary: 
Author: Iryna Halenok
Author-email: iryna.halenok@ut.ee
Requires-Python: >=3.9,<3.12
Classifier: Programming Language :: Python :: 3
Classifier: Programming Language :: Python :: 3.9
Classifier: Programming Language :: Python :: 3.10
Classifier: Programming Language :: Python :: 3.11
Requires-Dist: click (>=8.1.3,<9.0.0)
Requires-Dist: numpy (>=1.24.3,<2.0.0)
Requires-Dist: pandas (>=2.2.3,<3.0.0)
Requires-Dist: pix-framework (>=0.13.17,<0.14.0)
Requires-Dist: pylint (>=2.17.4,<3.0.0)
Requires-Dist: python-dateutil (>=2.8.2,<3.0.0)
Requires-Dist: pytz (>=2024.2,<2025.0)
Requires-Dist: scipy (>=1.13.0,<2.0.0)
